generate_argument_specs.py
ansible_argument_spec_generator-1.0.1.dist-info/licenses/LICENSE
ansible_argument_spec_generator-1.0.1.dist-info/METADATA
ansible_argument_spec_generator-1.0.1.dist-info/WHEEL
ansible_argument_spec_generator-1.0.1.dist-info/entry_points.txt
ansible_argument_spec_generator-1.0.1.dist-info/top_level.txt
ansible_argument_spec_generator-1.0.1.dist-info/RECORD
