Metadata-Version: 2.4
Name: ansible-argument-spec-generator
Version: 1.0.1
Summary: A comprehensive tool to generate argument_specs.yml files for Ansible collections and roles
Author-email: David Danielsson <djdanielsson@users.noreply.github.com>
License: MIT License
Project-URL: Homepage, https://github.com/djdanielsson/ansible_arg_spec_generator
Project-URL: Bug Reports, https://github.com/djdanielsson/ansible_arg_spec_generator/issues
Project-URL: Source, https://github.com/djdanielsson/ansible_arg_spec_generator
Project-URL: Documentation, https://github.com/djdanielsson/ansible_arg_spec_generator#readme
Keywords: ansible,automation,argument-specs,validation,documentation,yaml
Classifier: Development Status :: 5 - Production/Stable
Classifier: Intended Audience :: Developers
Classifier: Intended Audience :: System Administrators
Classifier: License :: OSI Approved :: MIT License
Classifier: Operating System :: OS Independent
Classifier: Topic :: Software Development :: Libraries :: Python Modules
Classifier: Topic :: System :: Systems Administration
Classifier: Programming Language :: Python :: 3.8
Classifier: Programming Language :: Python :: 3.9
Classifier: Programming Language :: Python :: 3.10
Classifier: Programming Language :: Python :: 3.11
Classifier: Programming Language :: Python :: 3.12
Classifier: Programming Language :: Python :: 3.13
Requires-Python: >=3.8
License-File: LICENSE
Requires-Dist: PyYAML>=5.1
Provides-Extra: dev
Requires-Dist: pytest>=6.0; extra == "dev"
Requires-Dist: pytest-cov>=4.0; extra == "dev"
Requires-Dist: pytest-mock>=3.10; extra == "dev"
Requires-Dist: black>=22.0; extra == "dev"
Requires-Dist: flake8>=5.0; extra == "dev"
Requires-Dist: mypy>=1.0; extra == "dev"
Provides-Extra: test
Requires-Dist: pytest>=6.0; extra == "test"
Requires-Dist: pytest-cov>=4.0; extra == "test"
Requires-Dist: pytest-mock>=3.10; extra == "test"
Dynamic: license-file
